{
  "$schema": "https://developer.microsoft.com/json-schemas/fabric/item/report/definition/visualContainer/2.4.0/schema.json",
  "name": "05ac9d563081523ddb2e",
  "position": {
    "x": 758.20765027322409,
    "y": 465.8360655737705,
    "z": 0,
    "height": 254.60109289617486,
    "width": 521.79234972677591,
    "tabOrder": 0
  },
  "visual": {
    "visualType": "tableEx",
    "query": {
      "queryState": {
        "Values": {
          "projections": [
            {
              "field": {
                "Column": {
                  "Expression": {
                    "SourceRef": {
                      "Entity": "fact_transaction"
                    }
                  },
                  "Property": "derived_drink_by_ingredient"
                }
              },
              "queryRef": "fact_transaction.derived_drink_by_ingredient",
              "nativeQueryRef": "Product Line",
              "displayName": "Product Line"
            },
            {
              "field": {
                "Aggregation": {
                  "Expression": {
                    "Column": {
                      "Expression": {
                        "SourceRef": {
                          "Entity": "fact_transaction"
                        }
                      },
                      "Property": "line_total"
                    }
                  },
                  "Function": 0
                }
              },
              "queryRef": "Sum(fact_transaction.line_total)",
              "nativeQueryRef": "Sales",
              "displayName": "Sales"
            },
            {
              "field": {
                "Measure": {
                  "Expression": {
                    "SourceRef": {
                      "Entity": "fact_transaction"
                    }
                  },
                  "Property": "Measure_Sales_Change_By_Product_Text"
                }
              },
              "queryRef": "fact_transaction.Measure_Sales_Change_By_Product",
              "nativeQueryRef": "% Week Over Week",
              "displayName": "% Week Over Week"
            }
          ]
        }
      },
      "sortDefinition": {
        "sort": [
          {
            "field": {
              "Measure": {
                "Expression": {
                  "SourceRef": {
                    "Entity": "fact_transaction"
                  }
                },
                "Property": "Measure_Sales_Change_By_Product_Text"
              }
            },
            "direction": "Ascending"
          }
        ]
      }
    },
    "objects": {
      "columnHeaders": [
        {
          "properties": {
            "alignment": {
              "expr": {
                "Literal": {
                  "Value": "'Center'"
                }
              }
            }
          }
        }
      ],
      "columnFormatting": [
        {
          "properties": {
            "alignment": {
              "expr": {
                "Literal": {
                  "Value": "'Center'"
                }
              }
            }
          },
          "selector": {
            "metadata": "fact_transaction.derived_drink_by_ingredient"
          }
        },
        {
          "properties": {
            "alignment": {
              "expr": {
                "Literal": {
                  "Value": "'Center'"
                }
              }
            }
          },
          "selector": {
            "metadata": "Sum(fact_transaction.line_total)"
          }
        },
        {
          "properties": {
            "alignment": {
              "expr": {
                "Literal": {
                  "Value": "'Center'"
                }
              }
            }
          },
          "selector": {
            "metadata": "fact_transaction.Measure_Sales_Change_By_Product"
          }
        }
      ],
      "total": [
        {
          "properties": {
            "totals": {
              "expr": {
                "Literal": {
                  "Value": "false"
                }
              }
            }
          }
        }
      ]
    },
    "drillFilterOtherVisuals": true
  }
}